ctxs/__init__.py
ctxs/contextobject.py
ctxs/contextthread.py
ctxs-0.0.1.dist-info/licenses/LICENSE
ctxs-0.0.1.dist-info/METADATA
ctxs-0.0.1.dist-info/WHEEL
ctxs-0.0.1.dist-info/top_level.txt
ctxs-0.0.1.dist-info/RECORD
