Metadata-Version: 2.4
Name: ctxs
Version: 0.0.1
Summary: Extra helpers for python contextmanager
Author-email: Max Sikström <max@pengi.se>
License-Expression: MIT
Project-URL: Homepage, https://github.com/pengi/ctxs
Classifier: Development Status :: 4 - Beta
Classifier: Intended Audience :: Developers
Classifier: Natural Language :: English
Classifier: Programming Language :: Python
Classifier: Programming Language :: Python :: 3
Requires-Python: >=3.11
License-File: LICENSE
Dynamic: license-file
